lltiler/__init__.py
lltiler/_version.py
lltiler/lltiler.py
lltiler/scripts/__init__.py
lltiler/scripts/generate_tile_makefile.py
lltiler/scripts/overlay_tiles.py
lltiler/scripts/pyramid_step.py
lltiler-0.0.2.dist-info/METADATA
lltiler-0.0.2.dist-info/WHEEL
lltiler-0.0.2.dist-info/entry_points.txt
lltiler-0.0.2.dist-info/top_level.txt
lltiler-0.0.2.dist-info/RECORD
