Metadata-Version: 2.1
Name: lltiler
Version: 0.0.2
Summary: The Lat-Lon Tiler is a small tool to create map tiles in sphericalmercator projection for the use with online map libraries likeLeaflet, OpenLayers, Mapbox etc...
Home-page: https://github.com/d70-t/lltiler
Author: Tobias Kölling
Author-email: tobias.koelling@physik.uni-muenchen.de
License: UNKNOWN
Platform: UNKNOWN
Classifier: Programming Language :: Python :: 3
Classifier: License :: OSI Approved :: MIT License
Classifier: Operating System :: OS Independent
Requires-Python: >=3
Requires-Dist: numpy
Requires-Dist: pillow
